htmlparsert/__init__.py
htmlparsert/parser.py
htmlparsert-0.1.0.dist-info/WHEEL
htmlparsert-0.1.0.dist-info/METADATA
htmlparsert-0.1.0.dist-info/RECORD
