Metadata-Version: 2.1
Name: htmlparsert
Version: 0.1.0
Summary: A lightweight, no dependency HTML parser for text processing
License: MIT
Author: Yohei Tamura
Author-email: tamuhey@gmail.com
Requires-Python: >=3.6,<4.0
Classifier: License :: OSI Approved :: MIT License
Classifier: Programming Language :: Python :: 3
Classifier: Programming Language :: Python :: 3.6
Classifier: Programming Language :: Python :: 3.7
Classifier: Programming Language :: Python :: 3.8
